{
"skeleton": {
	"hash": "yXoguZn2cIE",
	"spine": "4.2.43",
	"x": -133,
	"y": -134,
	"width": 267,
	"height": 267,
	"images": "./images/",
	"audio": "./audio"
},
"bones": [
	{ "name": "root" },
	{ "name": "Bomb", "parent": "root", "x": 2, "scaleX": 0.8625, "scaleY": 0.8625, "color": "00b4ffff" },
	{
		"name": "bomb rope",
		"parent": "Bomb",
		"length": 20.51,
		"rotation": -133.7,
		"x": -71.65,
		"y": 74.74,
		"color": "00b4ffff"
	},
	{
		"name": "bomb rope2",
		"parent": "bomb rope",
		"length": 15.36,
		"rotation": -81.7,
		"x": 24.41,
		"y": -3.12,
		"color": "00b4ffff"
	},
	{
		"name": "bomb rope3",
		"parent": "bomb rope2",
		"length": 21.52,
		"rotation": -94.64,
		"x": 17.46,
		"y": -5.79,
		"color": "00b4ffff"
	},
	{ "name": "bomb skull", "parent": "Bomb", "x": 38.07, "y": 5.29, "color": "00b4ffff" },
	{ "name": "water VFX", "parent": "Bomb", "y": -60.77, "color": "00b4ffff" }
],
"slots": [
	{ "name": "bg", "bone": "root", "attachment": "bg" },
	{ "name": "Bomb", "bone": "Bomb", "attachment": "bomb" },
	{ "name": "Bomb2", "bone": "Bomb", "color": "ffffff00", "attachment": "bomb", "blend": "additive" },
	{ "name": "Bomb3", "bone": "Bomb", "color": "ffffff00", "attachment": "bomb", "blend": "additive" },
	{ "name": "bomb skull", "bone": "bomb skull", "attachment": "bomb skull" },
	{ "name": "bomb rope", "bone": "bomb rope3", "attachment": "bomb rope" },
	{ "name": "bounding", "bone": "root", "attachment": "bounding" },
	{ "name": "water VFX", "bone": "water VFX", "color": "ffffff00", "attachment": "5", "blend": "additive" }
],
"physics": [
	{ "name": "bomb rope2", "bone": "bomb rope2", "rotate": 1, "inertia": 0.5, "damping": 0.85 },
	{ "name": "bomb rope3", "order": 1, "bone": "bomb rope3", "rotate": 1, "inertia": 0.5, "damping": 0.85 }
],
"skins": [
	{
		"name": "default",
		"attachments": {
			"bg": {
				"bg": { "x": 0.5, "y": -0.5, "width": 267, "height": 267 }
			},
			"Bomb": {
				"bomb": { "width": 192, "height": 222 }
			},
			"Bomb2": {
				"bomb": { "width": 192, "height": 222 }
			},
			"Bomb3": {
				"bomb": { "width": 192, "height": 222 }
			},
			"bomb rope": {
				"bomb rope": {
					"type": "mesh",
					"uvs": [ 0.47351, 0.021, 0.64312, 0.06634, 0.6438, 0.24384, 0.50901, 0.3947, 0.26219, 0.55903, 0.26309, 0.6736, 0.35754, 0.73237, 0.52441, 0.68752, 0.8661, 0.28901, 0.92464, 0.28737, 0.98567, 0.57798, 0.92796, 0.73375, 0.61393, 0.97887, 0.29699, 0.97846, 0.07933, 0.84209, 0.03935, 0.76236, 0.01152, 0.55554, 0.11822, 0.35597, 0.28175, 0.20284, 0.38056, 0.19065, 0.38064, 0.0661, 0.42843, 0.02192 ],
					"triangles": [ 2, 0, 1, 0, 2, 20, 2, 19, 20, 3, 19, 2, 18, 19, 3, 4, 18, 3, 6, 7, 12, 13, 6, 12, 12, 7, 11, 10, 7, 8, 11, 7, 10, 10, 8, 9, 5, 15, 16, 5, 16, 4, 14, 15, 5, 6, 14, 5, 13, 14, 6, 21, 0, 20, 4, 17, 18, 16, 17, 4 ],
					"vertices": [ 2, 4, 25.52, 3.77, 0.48067, 2, -4.03, -26.63, 0.51933, 2, 4, 28.54, -2.99, 0.18011, 2, -7.48, -20.07, 0.81989, 2, 4, 22.45, -8.15, 0.03104, 2, -1.72, -14.53, 0.96896, 3, 4, 13.61, -8.18, 0.15001, 3, 8.2, -18.69, 0.01337, 2, 7.1, -13.93, 0.83662, 3, 4, 1.28, -5, 0.32217, 3, 12.37, -6.66, 0.20954, 2, 19.6, -16.32, 0.46829, 3, 4, -2.65, -8.35, 0.14, 3, 9.35, -2.48, 0.37359, 2, 23.3, -12.73, 0.48641, 3, 4, -2.12, -13.09, 0.0073, 3, 4.59, -2.62, 0.33882, 2, 22.48, -8.03, 0.65388, 2, 3, 0.04, -8.32, 0.05572, 2, 16.18, -4.36, 0.94428, 1, 2, -6.7, -6.38, 1, 1, 2, -8.46, -4.65, 1, 1, 2, -0.77, 6.24, 1, 1, 2, 5.97, 9.33, 1, 1, 2, 23.06, 7.41, 1, 2, 3, 0.24, 7.88, 0.48967, 2, 32.24, -2.22, 0.51033, 2, 3, 11.25, 8.17, 0.83946, 2, 34.12, -13.07, 0.16054, 3, 4, -11.75, -3.72, 0.13788, 3, 14.7, 6.22, 0.76543, 2, 32.68, -16.76, 0.09669, 3, 4, -5.38, 3.16, 0.46122, 3, 21.04, -0.69, 0.48785, 2, 26.76, -24.04, 0.05093, 3, 4, 4.38, 5.51, 0.69208, 3, 22.59, -10.61, 0.15263, 2, 17.17, -27, 0.15529, 2, 4, 14.08, 4.68, 0.64962, 2, 7.45, -26.8, 0.35038, 2, 4, 17.17, 1.85, 0.49539, 2, 4.18, -24.18, 0.50461, 2, 4, 21.46, 5.46, 0.58744, 2, 0.13, -28.05, 0.41256, 2, 4, 24.27, 5.2, 0.5495, 2, -2.69, -27.97, 0.4505 ],
					"hull": 22,
					"edges": [ 0, 42, 0, 2, 2, 4, 4, 6, 6, 8, 8, 10, 10, 12, 12, 14, 14, 16, 16, 18, 18, 20, 20, 22, 22, 24, 24, 26, 26, 28, 28, 30, 30, 32, 32, 34, 34, 36, 36, 38, 38, 40, 40, 42 ],
					"width": 42,
					"height": 45
				}
			},
			"bomb skull": {
				"bomb skull": { "x": -12.57, "y": -6.79, "width": 119, "height": 107 }
			},
			"bounding": {
				"bounding": {
					"type": "boundingbox",
					"vertexCount": 4,
					"vertices": [ -132, 132.03, 133, 132.02, 133, -133, -132, -133 ]
				}
			},
			"water VFX": {
				"0": { "y": 35.57, "width": 25, "height": 14 },
				"1": { "y": 35.57, "width": 105, "height": 75 },
				"2": { "y": 35.57, "width": 149, "height": 144 },
				"3": { "y": 35.57, "width": 180, "height": 179 },
				"4": { "y": 35.57, "width": 198, "height": 149 },
				"5": { "width": 175, "height": 150 }
			}
		}
	}
],
"animations": {
	"animation": {
		"slots": {
			"Bomb2": {
				"rgba": [
					{ "time": 0.3333, "color": "ffffff00" },
					{ "time": 0.5, "color": "ffffffff" },
					{ "time": 0.6667, "color": "ffffff00" }
				]
			},
			"Bomb3": {
				"rgba": [
					{ "time": 0.3333, "color": "ffffff00" },
					{ "time": 0.5, "color": "ffffffff" },
					{ "time": 0.6667, "color": "ffffff00" }
				]
			},
			"water VFX": {
				"rgba": [
					{ "time": 0.3, "color": "ffffff00" },
					{ "time": 0.3333, "color": "ffffffff", "curve": "stepped" },
					{ "time": 0.6333, "color": "ffffffff" },
					{ "time": 0.6667, "color": "ffffff00" }
				],
				"attachment": [
					{ "time": 0.3333, "name": "0" },
					{ "time": 0.4, "name": "1" },
					{ "time": 0.4667, "name": "2" },
					{ "time": 0.5333, "name": "3" },
					{ "time": 0.6, "name": "4" },
					{ "time": 0.6667, "name": "5" }
				]
			}
		},
		"bones": {
			"Bomb": {
				"rotate": [
					{
						"curve": [ 0.056, 13.36, 0.026, 51.06 ]
					},
					{
						"time": 0.1667,
						"value": 25.92,
						"curve": [ 0.222, 16, 0.278, 9.52 ]
					},
					{
						"time": 0.3333,
						"value": -3.84,
						"curve": [ 0.389, -17.2, 0.444, -54.23 ]
					},
					{
						"time": 0.5,
						"value": -54.23,
						"curve": [ 0.556, -54.23, 0.611, -13.36 ]
					},
					{ "time": 0.6667 }
				],
				"translate": [
					{
						"curve": [ 0.056, 0, 0.004, -0.88, 0.056, 6.37, 0.031, 49.32 ]
					},
					{
						"time": 0.1667,
						"x": 8.74,
						"y": 21.85,
						"curve": [ 0.222, 12.02, 0.278, 15.66, 0.222, 10.56, 0.278, -7.65 ]
					},
					{
						"time": 0.3333,
						"x": 18.57,
						"y": -12.02,
						"curve": [ 0.389, 21.48, 0.444, 26.22, 0.389, -16.39, 0.444, -16.39 ]
					},
					{
						"time": 0.5,
						"x": 26.22,
						"y": -16.39,
						"curve": [ 0.556, 26.22, 0.611, 0, 0.556, -16.39, 0.611, -6.37 ]
					},
					{ "time": 0.6667 }
				],
				"scale": [
					{
						"curve": [ 0.056, 1, 0, 1.169, 0.056, 1, 0, 1.169 ]
					},
					{
						"time": 0.1667,
						"x": 1.169,
						"y": 1.169,
						"curve": [ 0.333, 1.169, 0.5, 1, 0.333, 1.169, 0.5, 1 ]
					},
					{ "time": 0.6667 }
				]
			},
			"bomb skull": {
				"rotate": [
					{
						"curve": [ 0.056, 3.71, 0.111, 4.79 ]
					},
					{
						"time": 0.1667,
						"value": 11.12,
						"curve": [ 0.278, 23.79, 0.389, 57 ]
					},
					{
						"time": 0.5,
						"value": 57,
						"curve": [ 0.556, 57, 0.611, 19 ]
					},
					{ "time": 0.6667 }
				],
				"translate": [
					{
						"curve": [ 0.056, 9.57, 0.111, 44.1, 0.056, 4.92, 0.111, 16.74 ]
					},
					{
						"time": 0.1667,
						"x": 44.1,
						"y": 23.78,
						"curve": [ 0.222, 44.1, 0.444, 26.74, 0.222, 30.82, 0.444, 16.84 ]
					},
					{
						"time": 0.5,
						"x": 26.74,
						"y": 16.84,
						"curve": [ 0.556, 26.74, 0.611, -3.71, 0.556, 16.84, 0.611, 18.9 ]
					},
					{ "time": 0.6667 }
				]
			}
		}
	}
}
}